huaweicloudsdkoms/__init__.py
huaweicloudsdkoms/v2/__init__.py
huaweicloudsdkoms/v2/oms_async_client.py
huaweicloudsdkoms/v2/oms_client.py
huaweicloudsdkoms/v2/model/__init__.py
huaweicloudsdkoms/v2/model/bandwidth_policy_dto.py
huaweicloudsdkoms/v2/model/batch_update_tasks_req.py
huaweicloudsdkoms/v2/model/batch_update_tasks_request.py
huaweicloudsdkoms/v2/model/batch_update_tasks_response.py
huaweicloudsdkoms/v2/model/check_prefix_req.py
huaweicloudsdkoms/v2/model/check_prefix_request.py
huaweicloudsdkoms/v2/model/check_prefix_response.py
huaweicloudsdkoms/v2/model/checked_key.py
huaweicloudsdkoms/v2/model/create_sync_events_request.py
huaweicloudsdkoms/v2/model/create_sync_events_response.py
huaweicloudsdkoms/v2/model/create_sync_task_req.py
huaweicloudsdkoms/v2/model/create_sync_task_request.py
huaweicloudsdkoms/v2/model/create_sync_task_response.py
huaweicloudsdkoms/v2/model/create_task_group_req.py
huaweicloudsdkoms/v2/model/create_task_group_request.py
huaweicloudsdkoms/v2/model/create_task_group_response.py
huaweicloudsdkoms/v2/model/create_task_req.py
huaweicloudsdkoms/v2/model/create_task_request.py
huaweicloudsdkoms/v2/model/create_task_response.py
huaweicloudsdkoms/v2/model/delete_sync_task_request.py
huaweicloudsdkoms/v2/model/delete_sync_task_response.py
huaweicloudsdkoms/v2/model/delete_task_group_request.py
huaweicloudsdkoms/v2/model/delete_task_group_response.py
huaweicloudsdkoms/v2/model/delete_task_request.py
huaweicloudsdkoms/v2/model/delete_task_response.py
huaweicloudsdkoms/v2/model/dst_node_req.py
huaweicloudsdkoms/v2/model/dst_node_resp.py
huaweicloudsdkoms/v2/model/error_reason_resp.py
huaweicloudsdkoms/v2/model/failed_object_record_dto.py
huaweicloudsdkoms/v2/model/link.py
huaweicloudsdkoms/v2/model/list_api_versions_request.py
huaweicloudsdkoms/v2/model/list_api_versions_response.py
huaweicloudsdkoms/v2/model/list_buckets_req.py
huaweicloudsdkoms/v2/model/list_file.py
huaweicloudsdkoms/v2/model/list_sync_task_statistic_request.py
huaweicloudsdkoms-3.1.184.dist-info/METADATA
huaweicloudsdkoms-3.1.184.dist-info/WHEEL
huaweicloudsdkoms-3.1.184.dist-info/licenses/LICENSE
huaweicloudsdkoms-3.1.184.dist-info/RECORD
